{
	"id": "Lurantis",
	"spawnInfos": [
		{
			"spec": {
				"name": "Lurantis"
			},
			"stringLocationTypes": [
				"Land",
				"Tree Top"
			],
			"minLevel": 34,
			"maxLevel": 50,
			"typeID": "pokemon",
			"heldItems": [
                {
                    "itemID": "pixelmon:miracle_seed",
                    "percentChance": 5
                }
            ],
			"condition": {
				"times": [
					"DAWN",
					"DUSK"
				],
				"stringBiomes": [
					"jungles"
				]
			},
			"rarityMultipliers": [
                {
                    "multiplier": 1.5,
                    "condition": {
                        "neededNearbyBlocks": [
                            "minecraft:yellow_flower"
                        ]
                    }
                }
            ],
			"rarity": 5.0
		}
	]
}